{
    "北京市": 6.35,
    "天津市": 5.3,
    "河北省": 7.15,
    "山西省": 7.06,
    "内蒙古自治区": 6.26,
    "辽宁省": 4.71,
    "吉林省": 4.7,
    "黑龙江省": 3.59,
    "上海市": 4.67,
    "江苏省": 5.65,
    "浙江省": 6.9,
    "安徽省": 8.05,
    "福建省": 8.26,
    "江西省": 8.34,
    "山东省": 7.38,
    "河南省": 8.0,
    "湖北省": 6.98,
    "湖南省": 7.13,
    "广东省": 9.35,
    "广西壮族自治区": 9.68,
    "海南省": 9.74,
    "重庆市": 6.49,
    "四川省": 6.85,
    "贵州省": 12.17,
    "云南省": 9.35,
    "西藏自治区": 14.17,
    "陕西省": 7.89,
    "甘肃省": 9.68,
    "青海省": 11.22,
    "宁夏回族自治区": 11.62,
    "新疆维吾尔自治区": 6.16
}