[
    {
        "年份": 2005,
        "GDP": 7149.8,
        "人口": 1538.0,
        "出生率": 6.29
    },
    {
        "年份": 2006,
        "GDP": 8387.0,
        "人口": 1601.0,
        "出生率": 6.26
    },
    {
        "年份": 2007,
        "GDP": 10425.5,
        "人口": 1676.0,
        "出生率": 8.32
    },
    {
        "年份": 2008,
        "GDP": 11813.1,
        "人口": 1771.0,
        "出生率": 8.17
    },
    {
        "年份": 2009,
        "GDP": 12900.9,
        "人口": 1860.0,
        "出生率": 8.06
    },
    {
        "年份": 2010,
        "GDP": 14964.0,
        "人口": 1962.0,
        "出生率": 7.48
    },
    {
        "年份": 2011,
        "GDP": 17188.8,
        "人口": 2024.0,
        "出生率": 8.29
    },
    {
        "年份": 2012,
        "GDP": 19024.7,
        "人口": 2078.0,
        "出生率": 9.05
    },
    {
        "年份": 2013,
        "GDP": 21134.6,
        "人口": 2125.0,
        "出生率": 8.93
    },
    {
        "年份": 2014,
        "GDP": 22926.0,
        "人口": 2171.0,
        "出生率": 9.75
    },
    {
        "年份": 2015,
        "GDP": 24779.1,
        "人口": 2188.0,
        "出生率": 7.96
    },
    {
        "年份": 2016,
        "GDP": 27041.2,
        "人口": 2195.0,
        "出生率": 9.32
    },
    {
        "年份": 2017,
        "GDP": 29883.0,
        "人口": 2194.0,
        "出生率": 9.06
    },
    {
        "年份": 2018,
        "GDP": 33106.0,
        "人口": 2192.0,
        "出生率": 8.24
    },
    {
        "年份": 2019,
        "GDP": 35445.1,
        "人口": 2190.0,
        "出生率": 8.12
    },
    {
        "年份": 2020,
        "GDP": 35943.3,
        "人口": 2189.0,
        "出生率": 6.99
    },
    {
        "年份": 2021,
        "GDP": 41045.6,
        "人口": 2189.0,
        "出生率": 6.35
    },
    {
        "年份": 2022,
        "GDP": 41540.9,
        "人口": 2184.0,
        "出生率": 5.67
    },
    {
        "年份": 2023,
        "GDP": 43760.7,
        "人口": 2186.0,
        "出生率": 5.63
    }
]